config/__init__.py
config/config.py
simple_configuration-1.0.0.dist-info/METADATA
simple_configuration-1.0.0.dist-info/WHEEL
simple_configuration-1.0.0.dist-info/top_level.txt
simple_configuration-1.0.0.dist-info/RECORD
